hello_world/__init__.py
kolawole_hello_world-0.3.4.dist-info/LICENSE
kolawole_hello_world-0.3.4.dist-info/METADATA
kolawole_hello_world-0.3.4.dist-info/WHEEL
kolawole_hello_world-0.3.4.dist-info/top_level.txt
kolawole_hello_world-0.3.4.dist-info/RECORD
