Metadata-Version: 2.1
Name: kolawole-hello-world
Version: 0.3.4
Summary: Read the latest Real Python tutorials
License-File: LICENSE
Requires-Dist: requests
Requires-Dist: pytest
Requires-Dist: importlib-metadata ; python_version < "3.8"
